invenio_webhooks/__init__.py
invenio_webhooks/_compat.py
invenio_webhooks/config.py
invenio_webhooks/errors.py
invenio_webhooks/ext.py
invenio_webhooks/models.py
invenio_webhooks/proxies.py
invenio_webhooks/signatures.py
invenio_webhooks/views.py
invenio_webhooks/alembic/469925575192_create_webhooks_branch.py
invenio_webhooks/alembic/a095bd179f5c_create_webhooks_tables.py
invenio_webhooks/translations/messages.pot
invenio_webhooks/translations/cs/LC_MESSAGES/messages.mo
invenio_webhooks/translations/cs/LC_MESSAGES/messages.po
invenio_webhooks/translations/da/LC_MESSAGES/messages.mo
invenio_webhooks/translations/da/LC_MESSAGES/messages.po
invenio_webhooks/translations/de/LC_MESSAGES/messages.mo
invenio_webhooks/translations/de/LC_MESSAGES/messages.po
invenio_webhooks/translations/es/LC_MESSAGES/messages.mo
invenio_webhooks/translations/es/LC_MESSAGES/messages.po
invenio_webhooks/translations/fr/LC_MESSAGES/messages.mo
invenio_webhooks/translations/fr/LC_MESSAGES/messages.po
invenio_webhooks/translations/it/LC_MESSAGES/messages.mo
invenio_webhooks/translations/it/LC_MESSAGES/messages.po
invenio_webhooks-1.1.0.dist-info/licenses/AUTHORS.rst
invenio_webhooks-1.1.0.dist-info/licenses/LICENSE
invenio_webhooks-1.1.0.dist-info/METADATA
invenio_webhooks-1.1.0.dist-info/WHEEL
invenio_webhooks-1.1.0.dist-info/entry_points.txt
invenio_webhooks-1.1.0.dist-info/top_level.txt
invenio_webhooks-1.1.0.dist-info/RECORD
