Metadata-Version: 2.4
Name: invenio-webhooks
Version: 1.1.0
Summary: "Invenio webhooks module to create REST APIs."
Home-page: https://github.com/inveniosoftware/invenio-webhooks
Author: CERN
Author-email: info@inveniosoftware.org
License: MIT
Keywords: invenio webhooks
Platform: any
Classifier: Environment :: Web Environment
Classifier: Intended Audience :: Developers
Classifier: Operating System :: OS Independent
Classifier: Programming Language :: Python
Classifier: Topic :: Internet :: WWW/HTTP :: Dynamic Content
Classifier: Topic :: Software Development :: Libraries :: Python Modules
Classifier: Programming Language :: Python :: 3
Classifier: Programming Language :: Python :: 3.7
Classifier: Programming Language :: Python :: 3.8
Classifier: Programming Language :: Python :: 3.9
Classifier: Programming Language :: Python :: Implementation :: CPython
Classifier: Development Status :: 1 - Planning
Requires-Python: >=3.7
License-File: LICENSE
License-File: AUTHORS.rst
Requires-Dist: invenio-base>=2.3.0
Requires-Dist: invenio-i18n>=1.3.2
Requires-Dist: invenio-oauthclient>=2.0.1
Requires-Dist: invenio-oauth2server>=1.3.6
Provides-Extra: tests
Requires-Dist: pytest-black>=0.3.0; extra == "tests"
Requires-Dist: invenio-app>=1.3.2; extra == "tests"
Requires-Dist: invenio-celery>=1.2.4; extra == "tests"
Requires-Dist: invenio-db[mysql,postgresql,versioning]>=1.0.14; extra == "tests"
Requires-Dist: invenio-cli>=1.0.5; extra == "tests"
Requires-Dist: pytest-invenio>=1.4.13; extra == "tests"
Requires-Dist: sphinx>=4.2.0; extra == "tests"
Dynamic: license-file
